pennylane_honeywell/__init__.py
pennylane_honeywell/_version.py
pennylane_honeywell/device.py
PennyLane_Honeywell-0.34.1.dist-info/LICENSE
PennyLane_Honeywell-0.34.1.dist-info/METADATA
PennyLane_Honeywell-0.34.1.dist-info/WHEEL
PennyLane_Honeywell-0.34.1.dist-info/entry_points.txt
PennyLane_Honeywell-0.34.1.dist-info/top_level.txt
PennyLane_Honeywell-0.34.1.dist-info/RECORD
