Metadata-Version: 2.1
Name: PennyLane-Honeywell
Version: 0.34.1
Summary: PennyLane plugin to access the Honeywell Quantum Solutions cloud service.
Home-page: http://xanadu.ai
Maintainer: Xanadu Inc.
License: Apache License 2.0
Platform: UNKNOWN
Classifier: Development Status :: 4 - Beta
Classifier: Environment :: Console
Classifier: Intended Audience :: Science/Research
Classifier: License :: OSI Approved :: Apache Software License
Classifier: Natural Language :: English
Classifier: Operating System :: POSIX
Classifier: Operating System :: MacOS :: MacOS X
Classifier: Operating System :: POSIX :: Linux
Classifier: Operating System :: Microsoft :: Windows
Classifier: Programming Language :: Python
Classifier: Programming Language :: Python :: 3
Classifier: Programming Language :: Python :: 3.9
Classifier: Programming Language :: Python :: 3.10
Classifier: Programming Language :: Python :: 3.11
Classifier: Programming Language :: Python :: 3 :: Only
Classifier: Topic :: Scientific/Engineering :: Physics
Provides: pennylane_honeywell
License-File: LICENSE
Requires-Dist: pennylane <0.35,>=0.30
Requires-Dist: requests
Requires-Dist: pyjwt
Requires-Dist: toml
